kurator/__init__.py
kurator/command_line.py
kurator/kurator.py
kurator-0.1.dist-info/DESCRIPTION.rst
kurator-0.1.dist-info/METADATA
kurator-0.1.dist-info/RECORD
kurator-0.1.dist-info/WHEEL
kurator-0.1.dist-info/entry_points.txt
kurator-0.1.dist-info/metadata.json
kurator-0.1.dist-info/top_level.txt
