Metadata-Version: 2.0
Name: kurator
Version: 0.1
Summary: Command line tool to help with media dumps
Home-page: http://github.com/saltycatfish/kurator
Author: SaltyCatFish
Author-email: ryan@saltycatfish.com
License: MIT
Download-URL: https://github.com/saltycatfish/kurator/archive/0.1.tar.gz
Keywords: media,dump,file,transfer,exif,photos,images,duplicate,rename
Platform: UNKNOWN
Requires-Dist: click (==6.7)
Requires-Dist: ExifRead (==2.1.2)
Requires-Dist: olefile (==0.44)
Requires-Dist: Pillow (==4.2.1)
Requires-Dist: psycopg2 (==2.7.3.1)
Requires-Dist: pyasn1 (==0.3.6)
Requires-Dist: pyasn1-modules (==0.1.4)
Requires-Dist: rsa (==3.4.2)
Requires-Dist: six (==1.11.0)
Requires-Dist: uritemplate (==3.0.0)
